{"trial_id": "0013", "hyperparameters": {"space": [{"class_name": "Choice", "config": {"name": "units_1", "default": 32, "conditions": [], "values": [32, 64, 128], "ordered": true}}, {"class_name": "Choice", "config": {"name": "optimizer", "default": "adam", "conditions": [], "values": ["adam", "sgd", "rmsprop", "adamw"], "ordered": false}}, {"class_name": "Choice", "config": {"name": "learning_rate", "default": 0.0001, "conditions": [], "values": [0.0001, 0.001, 0.01, 0.1], "ordered": true}}], "values": {"units_1": 64, "optimizer": "rmsprop", "learning_rate": 0.001, "tuner/epochs": 4, "tuner/initial_epoch": 2, "tuner/bracket": 2, "tuner/round": 1, "tuner/trial_id": "0005"}}, "metrics": {"metrics": {"accuracy": {"direction": "max", "observations": [{"value": [0.9918069839477539], "step": 1}]}, "loss": {"direction": "min", "observations": [{"value": [0.024305559694767], "step": 1}]}, "val_accuracy": {"direction": "max", "observations": [{"value": [0.9932379722595215], "step": 1}]}, "val_loss": {"direction": "min", "observations": [{"value": [0.019547240808606148], "step": 1}]}}}, "score": 0.9932379722595215, "best_step": 1, "status": "COMPLETED", "message": null}